CobWeb/__init__.py
CobWeb/crawler.py
CobWeb_lnx-1.1.0.dist-info/LICENSE.md
CobWeb_lnx-1.1.0.dist-info/METADATA
CobWeb_lnx-1.1.0.dist-info/WHEEL
CobWeb_lnx-1.1.0.dist-info/top_level.txt
CobWeb_lnx-1.1.0.dist-info/RECORD
