Metadata-Version: 2.1
Name: CobWeb-lnx
Version: 1.1.0
Summary: CobWeb is a Python library for web scraping. The library consists of two classes: Spider and Scraper.
Author-email: "Gonçalo Marques (_lnx/lnxdread)" <gmgoncalo7@gmail.com>
Project-URL: Homepage, https://github.com/GoncaloMark/Amara-CobWeb
Project-URL: Bug Tracker, https://github.com/GoncaloMark/Amara-CobWeb/issues
Keywords: data,crawler,scraper
Classifier: Programming Language :: Python :: 3
Classifier: License :: OSI Approved :: MIT License
Classifier: Operating System :: OS Independent
Requires-Python: >=3.7
License-File: LICENSE.md
Requires-Dist: aiohttp (==3.8.4)
Requires-Dist: aiosignal (==1.3.1)
Requires-Dist: async-timeout (==4.0.2)
Requires-Dist: attrs (==22.2.0)
Requires-Dist: beautifulsoup4 (==4.11.2)
Requires-Dist: certifi (==2022.12.7)
Requires-Dist: charset-normalizer (==3.0.1)
Requires-Dist: frozenlist (==1.3.3)
Requires-Dist: idna (==3.4)
Requires-Dist: jsonschema (==4.17.3)
Requires-Dist: lxml (==4.9.2)
Requires-Dist: multidict (==6.0.4)
Requires-Dist: pyproject-toml (==0.0.10)
Requires-Dist: pyrsistent (==0.19.3)
Requires-Dist: PyYAML (==6.0)
Requires-Dist: six (==1.16.0)
Requires-Dist: soupsieve (==2.3.2.post1)
Requires-Dist: toml (==0.10.2)
Requires-Dist: urllib3 (==1.26.14)
Requires-Dist: webencodings (==0.5.1)
Requires-Dist: yarl (==1.9.2)
